ubcpdk/README.md
ubcpdk/__init__.py
ubcpdk/config.py
ubcpdk/import_gds.py
ubcpdk/layers.yaml
ubcpdk/models.py
ubcpdk/tech.py
ubcpdk/cells/__init__.py
ubcpdk/cells/containers.py
ubcpdk/cells/couplers.py
ubcpdk/cells/die_with_pads.py
ubcpdk/cells/fixed_ant.py
ubcpdk/cells/fixed_beta.py
ubcpdk/cells/fixed_dream.py
ubcpdk/cells/fixed_ebeam.py
ubcpdk/cells/fixed_single.py
ubcpdk/cells/grating_couplers.py
ubcpdk/cells/heaters.py
ubcpdk/cells/mmis.py
ubcpdk/cells/mzis.py
ubcpdk/cells/rings.py
ubcpdk/cells/spirals.py
ubcpdk/cells/tapers.py
ubcpdk/cells/text.py
ubcpdk/cells/vias.py
ubcpdk/cells/waveguides.py
ubcpdk/data/__init__.py
ubcpdk/data/chop.py
ubcpdk/data/convert_to_pandas.py
ubcpdk/data/dbr.md
ubcpdk/data/dbr.py
ubcpdk/data/find_bandwidth.py
ubcpdk/data/read_mat.py
ubcpdk/data/remove_baseline.py
ubcpdk/data/windowed_mean.py
ubcpdk/gds/ANT/ebeam_splitter_swg_assist_te1310_ANT.GDS
ubcpdk/gds/ANT/ebeam_splitter_swg_assist_te1550_ANT.GDS
ubcpdk/gds/EBeam/GC_TE_1310_8degOxide_BB.gds
ubcpdk/gds/EBeam/GC_TE_1550_8degOxide_BB.gds
ubcpdk/gds/EBeam/GC_TM_1310_8degOxide_BB.gds
ubcpdk/gds/EBeam/GC_TM_1550_8degOxide_BB.gds
ubcpdk/gds/EBeam/GCs_BB.gds
ubcpdk/gds/EBeam/ebeam_adiabatic_te1550.gds
ubcpdk/gds/EBeam/ebeam_adiabatic_tm1550.gds
ubcpdk/gds/EBeam/ebeam_bdc_te1550.gds
ubcpdk/gds/EBeam/ebeam_crossing4.gds
ubcpdk/gds/EBeam/ebeam_gc_te1550.gds
ubcpdk/gds/EBeam/ebeam_gc_tm1550.gds
ubcpdk/gds/EBeam/ebeam_routing_taper_te1550_w=500nm_to_w=3000nm_L=20um.gds
ubcpdk/gds/EBeam/ebeam_routing_taper_te1550_w=500nm_to_w=3000nm_L=40um.gds
ubcpdk/gds/EBeam/ebeam_splitter_swg_assist_te1310.gds
ubcpdk/gds/EBeam/ebeam_splitter_swg_assist_te1550.gds
ubcpdk/gds/EBeam/ebeam_terminator_te1310.gds
ubcpdk/gds/EBeam/ebeam_terminator_te1550.gds
ubcpdk/gds/EBeam/ebeam_terminator_tm1550.gds
ubcpdk/gds/EBeam/ebeam_y_1310.gds
ubcpdk/gds/EBeam/ebeam_y_1550.gds
ubcpdk/gds/EBeam/ebeam_y_adiabatic.gds
ubcpdk/gds/EBeam/ebeam_y_adiabatic_500pin.gds
ubcpdk/gds/EBeam/taper_si_simm_1310.gds
ubcpdk-3.2.0.dist-info/licenses/LICENSE
ubcpdk-3.2.0.dist-info/WHEEL
ubcpdk-3.2.0.dist-info/METADATA
ubcpdk-3.2.0.dist-info/RECORD
