Metadata-Version: 2.4
Name: ubcpdk
Version: 3.2.0
Summary: ubcpdk pdk
Keywords: python
Author-email: gdsfactory <contact@gdsfactory.com>
Requires-Python: >=3.11,<3.13
Classifier: License :: OSI Approved :: MIT License
Classifier: Programming Language :: Python :: 3.11
Classifier: Programming Language :: Python :: 3.12
Classifier: Operating System :: OS Independent
License-File: LICENSE
Requires-Dist: gdsfactory~=9.14.0
Requires-Dist: gplugins[sax, tidy3d]~=1.4.2
Requires-Dist: jsondiff
Requires-Dist: doroutes>=0.2.0
Requires-Dist: pytest ; extra == "dev"
Requires-Dist: pytest-cov ; extra == "dev"
Requires-Dist: pytest_regressions ; extra == "dev"
Requires-Dist: pytest-github-actions-annotate-failures ; extra == "dev"
Requires-Dist: pre-commit ; extra == "dev"
Requires-Dist: autodoc_pydantic ; extra == "docs"
Requires-Dist: jupytext ; extra == "docs"
Requires-Dist: jupyter-book==1.0.3 ; extra == "docs"
Provides-Extra: dev
Provides-Extra: docs
